odoo10_addon_mgmtsystem_survey-10.0.1.0.0-py2.7-nspkg.pth
odoo10_addon_mgmtsystem_survey-10.0.1.0.0.dist-info/top_level.txt
odoo10_addon_mgmtsystem_survey-10.0.1.0.0.dist-info/WHEEL
odoo10_addon_mgmtsystem_survey-10.0.1.0.0.dist-info/RECORD
odoo10_addon_mgmtsystem_survey-10.0.1.0.0.dist-info/metadata.json
odoo10_addon_mgmtsystem_survey-10.0.1.0.0.dist-info/DESCRIPTION.rst
odoo10_addon_mgmtsystem_survey-10.0.1.0.0.dist-info/METADATA
odoo10_addon_mgmtsystem_survey-10.0.1.0.0.dist-info/namespace_packages.txt
odoo/addons/mgmtsystem_survey/__manifest__.py
odoo/addons/mgmtsystem_survey/__init__.py
odoo/addons/mgmtsystem_survey/README.rst
odoo/addons/mgmtsystem_survey/i18n/lv.po
odoo/addons/mgmtsystem_survey/i18n/pt.po
odoo/addons/mgmtsystem_survey/i18n/es.po
odoo/addons/mgmtsystem_survey/i18n/tr.po
odoo/addons/mgmtsystem_survey/i18n/nn.po
odoo/addons/mgmtsystem_survey/i18n/hu.po
odoo/addons/mgmtsystem_survey/i18n/sl.po
odoo/addons/mgmtsystem_survey/i18n/th.po
odoo/addons/mgmtsystem_survey/i18n/nb.po
odoo/addons/mgmtsystem_survey/i18n/de.po
odoo/addons/mgmtsystem_survey/i18n/vi.po
odoo/addons/mgmtsystem_survey/i18n/fr.po
odoo/addons/mgmtsystem_survey/i18n/pt_BR.po
odoo/addons/mgmtsystem_survey/i18n/sv.po
odoo/addons/mgmtsystem_survey/i18n/mgmtsystem_survey.pot
odoo/addons/mgmtsystem_survey/i18n/fi.po
odoo/addons/mgmtsystem_survey/views/survey_survey.xml
odoo/addons/mgmtsystem_survey/data/survey_stage.xml
odoo/addons/mgmtsystem_survey/static/description/icon.png
